{
  "panels": [
    {
      "collapsed": false,
      "gridPos": {
        "h": 1,
        "w": 24,
        "x": 0,
        "y": 0
      },
      "title": "Fleet Overview",
      "type": "row"
    },
    {
      "datasource": {
        "uid": "PBFA97CFB590B2093"
      },
      "fieldConfig": {
        "defaults": {
          "thresholds": {
            "steps": [
              {
                "color": "green",
                "value": 0
              }
            ]
          }
        }
      },
      "gridPos": {
        "h": 4,
        "w": 4,
        "x": 0,
        "y": 1
      },
      "options": {
        "colorMode": "background",
        "graphMode": "none"
      },
      "targets": [
        {
          "expr": "count(pipeline_state == 1) or vector(0)",
          "instant": true,
          "refId": "A"
        }
      ],
      "title": "Running",
      "type": "stat"
    },
    {
      "datasource": {
        "uid": "PBFA97CFB590B2093"
      },
      "fieldConfig": {
        "defaults": {
          "thresholds": {
            "steps": [
              {
                "color": "green",
                "value": 0
              },
              {
                "color": "orange",
                "value": 1
              }
            ]
          }
        }
      },
      "gridPos": {
        "h": 4,
        "w": 4,
        "x": 4,
        "y": 1
      },
      "options": {
        "colorMode": "background",
        "graphMode": "none"
      },
      "targets": [
        {
          "expr": "count(pipeline_state == 0.5) or vector(0)",
          "instant": true,
          "refId": "A"
        }
      ],
      "title": "Degraded",
      "type": "stat"
    },
    {
      "datasource": {
        "uid": "PBFA97CFB590B2093"
      },
      "fieldConfig": {
        "defaults": {
          "thresholds": {
            "steps": [
              {
                "color": "green",
                "value": 0
              },
              {
                "color": "red",
                "value": 1
              }
            ]
          }
        }
      },
      "gridPos": {
        "h": 4,
        "w": 4,
        "x": 8,
        "y": 1
      },
      "options": {
        "colorMode": "background",
        "graphMode": "none"
      },
      "targets": [
        {
          "expr": "count(pipeline_state == 0) or vector(0)",
          "instant": true,
          "refId": "A"
        }
      ],
      "title": "Down",
      "type": "stat"
    },
    {
      "datasource": {
        "uid": "PBFA97CFB590B2093"
      },
      "fieldConfig": {
        "defaults": {
          "decimals": 1,
          "thresholds": {
            "steps": [
              {
                "color": "blue",
                "value": 0
              }
            ]
          }
        }
      },
      "gridPos": {
        "h": 4,
        "w": 4,
        "x": 12,
        "y": 1
      },
      "options": {
        "graphMode": "area"
      },
      "targets": [
        {
          "expr": "sum(rate(scte35_events_detected_total[5m])) * 60 or vector(0)",
          "instant": true,
          "refId": "A"
        }
      ],
      "title": "Detections/min",
      "type": "stat"
    },
    {
      "datasource": {
        "uid": "PBFA97CFB590B2093"
      },
      "fieldConfig": {
        "defaults": {
          "decimals": 1,
          "thresholds": {
            "steps": [
              {
                "color": "purple",
                "value": 0
              }
            ]
          }
        }
      },
      "gridPos": {
        "h": 4,
        "w": 4,
        "x": 16,
        "y": 1
      },
      "options": {
        "graphMode": "area"
      },
      "targets": [
        {
          "expr": "sum(rate(scte35_events_injected_total[5m])) * 60 or vector(0)",
          "instant": true,
          "refId": "A"
        }
      ],
      "title": "Injections/min",
      "type": "stat"
    },
    {
      "datasource": {
        "uid": "PBFA97CFB590B2093"
      },
      "fieldConfig": {
        "defaults": {
          "decimals": 1,
          "max": 100,
          "min": 0,
          "thresholds": {
            "steps": [
              {
                "color": "green",
                "value": 0
              },
              {
                "color": "orange",
                "value": 5
              },
              {
                "color": "red",
                "value": 20
              }
            ]
          },
          "unit": "percent"
        }
      },
      "gridPos": {
        "h": 4,
        "w": 4,
        "x": 20,
        "y": 1
      },
      "targets": [
        {
          "expr": "sum(rate(manifest_poll_errors_total[5m])) / sum(rate(manifest_poll_total[5m])) * 100",
          "instant": true,
          "refId": "A"
        }
      ],
      "title": "Poll Error Rate",
      "type": "gauge"
    },
    {
      "datasource": {
        "uid": "PBFA97CFB590B2093"
      },
      "fieldConfig": {
        "defaults": {
          "custom": {
            "fillOpacity": 15,
            "lineWidth": 2
          }
        }
      },
      "gridPos": {
        "h": 6,
        "w": 16,
        "x": 0,
        "y": 5
      },
      "targets": [
        {
          "expr": "sum(rate(scte35_events_detected_total[5m])) * 60",
          "legendFormat": "detected/min",
          "refId": "A"
        },
        {
          "expr": "sum(rate(scte35_events_injected_total[5m])) * 60",
          "legendFormat": "injected/min",
          "refId": "B"
        }
      ],
      "title": "Fleet Detection & Injection Rate",
      "type": "timeseries"
    },
    {
      "datasource": {
        "uid": "PBFA97CFB590B2093"
      },
      "fieldConfig": {
        "defaults": {
          "color": {
            "fixedColor": "orange",
            "mode": "fixed"
          },
          "custom": {
            "drawStyle": "bars",
            "fillOpacity": 60
          }
        }
      },
      "gridPos": {
        "h": 6,
        "w": 8,
        "x": 16,
        "y": 5
      },
      "targets": [
        {
          "expr": "sum(increase(pipeline_restarts_total[5m]))",
          "legendFormat": "restarts/5m",
          "refId": "A"
        }
      ],
      "title": "Fleet Restarts",
      "type": "timeseries"
    },
    {
      "collapsed": false,
      "gridPos": {
        "h": 1,
        "w": 24,
        "x": 0,
        "y": 11
      },
      "title": "All Pipelines (click row to drilldown)",
      "type": "row"
    },
    {
      "datasource": {
        "uid": "PBFA97CFB590B2093"
      },
      "fieldConfig": {
        "defaults": {
          "custom": {
            "align": "center",
            "filterable": true
          }
        },
        "overrides": [
          {
            "matcher": {
              "id": "byName",
              "options": "Pipeline"
            },
            "properties": [
              {
                "id": "custom.width",
                "value": 120
              },
              {
                "id": "links",
                "value": [
                  {
                    "title": "Drilldown ${__data.fields.Pipeline}",
                    "url": "/d/adb67b1a-a553-46b7-950d-d1bd7a62b368/hls-scte35-alert-drilldowns?var-pipeline=${__data.fields.Pipeline}&from=${__from}&to=${__to}"
                  }
                ]
              }
            ]
          },
          {
            "matcher": {
              "id": "byName",
              "options": "State"
            },
            "properties": [
              {
                "id": "custom.width",
                "value": 100
              },
              {
                "id": "mappings",
                "value": [
                  {
                    "options": {
                      "0": {
                        "color": "red",
                        "text": "DOWN"
                      }
                    },
                    "type": "value"
                  },
                  {
                    "options": {
                      "0.5": {
                        "color": "orange",
                        "text": "DEGRADED"
                      }
                    },
                    "type": "value"
                  },
                  {
                    "options": {
                      "1": {
                        "color": "green",
                        "text": "RUNNING"
                      }
                    },
                    "type": "value"
                  }
                ]
              },
              {
                "id": "custom.cellOptions",
                "value": {
                  "type": "color-background"
                }
              }
            ]
          },
          {
            "matcher": {
              "id": "byName",
              "options": "Detect/min"
            },
            "properties": [
              {
                "id": "decimals",
                "value": 1
              },
              {
                "id": "custom.width",
                "value": 100
              }
            ]
          },
          {
            "matcher": {
              "id": "byName",
              "options": "Inject/min"
            },
            "properties": [
              {
                "id": "decimals",
                "value": 1
              },
              {
                "id": "custom.width",
                "value": 100
              }
            ]
          },
          {
            "matcher": {
              "id": "byName",
              "options": "Restarts (1h)"
            },
            "properties": [
              {
                "id": "decimals",
                "value": 0
              },
              {
                "id": "custom.width",
                "value": 110
              },
              {
                "id": "thresholds",
                "value": {
                  "steps": [
                    {
                      "color": "green",
                      "value": 0
                    },
                    {
                      "color": "orange",
                      "value": 1
                    },
                    {
                      "color": "red",
                      "value": 3
                    }
                  ]
                }
              },
              {
                "id": "custom.cellOptions",
                "value": {
                  "type": "color-text"
                }
              }
            ]
          },
          {
            "matcher": {
              "id": "byName",
              "options": "Err %"
            },
            "properties": [
              {
                "id": "decimals",
                "value": 1
              },
              {
                "id": "unit",
                "value": "percent"
              },
              {
                "id": "custom.width",
                "value": 80
              },
              {
                "id": "thresholds",
                "value": {
                  "steps": [
                    {
                      "color": "green",
                      "value": 0
                    },
                    {
                      "color": "orange",
                      "value": 5
                    },
                    {
                      "color": "red",
                      "value": 20
                    }
                  ]
                }
              },
              {
                "id": "custom.cellOptions",
                "value": {
                  "type": "color-text"
                }
              }
            ]
          }
        ]
      },
      "gridPos": {
        "h": 12,
        "w": 24,
        "x": 0,
        "y": 12
      },
      "options": {
        "footer": {
          "countRows": true,
          "reducer": [
            "count"
          ],
          "show": true
        },
        "showHeader": true,
        "sortBy": [
          {
            "desc": false,
            "displayName": "State"
          }
        ]
      },
      "targets": [
        {
          "expr": "pipeline_state >= 0",
          "format": "table",
          "instant": true,
          "refId": "state"
        },
        {
          "expr": "sum by (id) (rate(scte35_events_detected_total[5m])) * 60",
          "format": "table",
          "instant": true,
          "refId": "detections"
        },
        {
          "expr": "sum by (id) (rate(scte35_events_injected_total[5m])) * 60",
          "format": "table",
          "instant": true,
          "refId": "injections"
        },
        {
          "expr": "sum by (id) (increase(pipeline_restarts_total[1h]))",
          "format": "table",
          "instant": true,
          "refId": "restarts"
        },
        {
          "expr": "sum by (id) (rate(manifest_poll_errors_total[5m])) / sum by (id) (rate(manifest_poll_total[5m])) * 100",
          "format": "table",
          "instant": true,
          "refId": "errors"
        }
      ],
      "title": "Pipeline Fleet",
      "transformations": [
        {
          "id": "seriesToColumns",
          "options": {
            "byField": "id"
          }
        },
        {
          "id": "organize",
          "options": {
            "excludeByName": {
              "Time": true,
              "Time 1": true,
              "Time 2": true,
              "Time 3": true,
              "Time 4": true,
              "Time 5": true,
              "__name__": true,
              "__name__ 1": true,
              "__name__ 2": true,
              "__name__ 3": true,
              "__name__ 4": true,
              "instance": true,
              "instance 1": true,
              "instance 2": true,
              "instance 3": true,
              "instance 4": true,
              "job": true,
              "job 1": true,
              "job 2": true,
              "job 3": true,
              "job 4": true
            },
            "renameByName": {
              "Value #detections": "Detect/min",
              "Value #errors": "Err %",
              "Value #injections": "Inject/min",
              "Value #restarts": "Restarts (1h)",
              "Value #state": "State",
              "id": "Pipeline"
            }
          }
        }
      ],
      "type": "table"
    },
    {
      "collapsed": false,
      "gridPos": {
        "h": 1,
        "w": 24,
        "x": 0,
        "y": 24
      },
      "title": "Pipeline Detail: $pipeline",
      "type": "row"
    },
    {
      "datasource": {
        "uid": "PBFA97CFB590B2093"
      },
      "fieldConfig": {
        "defaults": {
          "mappings": [
            {
              "options": {
                "0": {
                  "color": "red",
                  "text": "DOWN"
                }
              },
              "type": "value"
            },
            {
              "options": {
                "0.5": {
                  "color": "orange",
                  "text": "DEGRADED"
                }
              },
              "type": "value"
            },
            {
              "options": {
                "1": {
                  "color": "green",
                  "text": "RUNNING"
                }
              },
              "type": "value"
            }
          ]
        }
      },
      "gridPos": {
        "h": 3,
        "w": 24,
        "x": 0,
        "y": 25
      },
      "options": {
        "alignValue": "center",
        "mergeValues": true,
        "rowHeight": 0.9,
        "showValue": "auto"
      },
      "targets": [
        {
          "expr": "pipeline_state{id=~\"$pipeline\"}",
          "legendFormat": "{{id}}",
          "refId": "A"
        }
      ],
      "title": "State — $pipeline",
      "type": "state-timeline"
    },
    {
      "datasource": {
        "uid": "PBFA97CFB590B2093"
      },
      "fieldConfig": {
        "defaults": {
          "custom": {
            "fillOpacity": 20,
            "lineWidth": 2,
            "stacking": {
              "mode": "normal"
            }
          },
          "noValue": "No events detected",
          "unit": "events/min"
        },
        "overrides": [
          {
            "matcher": {
              "id": "byName",
              "options": "cue_out"
            },
            "properties": [
              {
                "id": "color",
                "value": {
                  "fixedColor": "red",
                  "mode": "fixed"
                }
              }
            ]
          },
          {
            "matcher": {
              "id": "byName",
              "options": "cue_in"
            },
            "properties": [
              {
                "id": "color",
                "value": {
                  "fixedColor": "green",
                  "mode": "fixed"
                }
              }
            ]
          },
          {
            "matcher": {
              "id": "byName",
              "options": "splice_insert"
            },
            "properties": [
              {
                "id": "color",
                "value": {
                  "fixedColor": "blue",
                  "mode": "fixed"
                }
              }
            ]
          }
        ]
      },
      "gridPos": {
        "h": 9,
        "w": 12,
        "x": 0,
        "y": 28
      },
      "targets": [
        {
          "expr": "rate(scte35_events_detected_total{id=~\"$pipeline\"}[5m]) * 60",
          "legendFormat": "{{type}}",
          "refId": "A"
        }
      ],
      "title": "SCTE-35 Detections — $pipeline",
      "type": "timeseries"
    },
    {
      "datasource": {
        "uid": "PBFA97CFB590B2093"
      },
      "fieldConfig": {
        "defaults": {
          "custom": {
            "fillOpacity": 20,
            "lineWidth": 2,
            "stacking": {
              "mode": "normal"
            }
          },
          "noValue": "No events injected",
          "unit": "events/min"
        },
        "overrides": [
          {
            "matcher": {
              "id": "byName",
              "options": "xml"
            },
            "properties": [
              {
                "id": "color",
                "value": {
                  "fixedColor": "purple",
                  "mode": "fixed"
                }
              }
            ]
          },
          {
            "matcher": {
              "id": "byName",
              "options": "binary"
            },
            "properties": [
              {
                "id": "color",
                "value": {
                  "fixedColor": "orange",
                  "mode": "fixed"
                }
              }
            ]
          }
        ]
      },
      "gridPos": {
        "h": 9,
        "w": 12,
        "x": 12,
        "y": 28
      },
      "targets": [
        {
          "expr": "rate(scte35_events_injected_total{id=~\"$pipeline\"}[5m]) * 60",
          "legendFormat": "{{format}}",
          "refId": "A"
        }
      ],
      "title": "SCTE-35 Injections — $pipeline",
      "type": "timeseries"
    }
  ],
  "refresh": "15s",
  "tags": [
    "hls-scte35",
    "alerts"
  ],
  "templating": {
    "list": [
      {
        "current": {
          "text": "121588af",
          "value": "121588af"
        },
        "datasource": {
          "uid": "PBFA97CFB590B2093"
        },
        "includeAll": false,
        "multi": false,
        "name": "pipeline",
        "query": "label_values(pipeline_state, id)",
        "refresh": 2,
        "sort": 1,
        "type": "query"
      }
    ]
  },
  "time": {
    "from": "now-3h",
    "to": "now"
  },
  "timezone": "browser",
  "title": "hls-scte35 Alert Drilldowns",
  "uid": "adb67b1a-a553-46b7-950d-d1bd7a62b368"
}
